LICENSE
README.md
setup.py
spellfix.c
sqlite_spellfix.py
sqlite_spellfix.egg-info/PKG-INFO
sqlite_spellfix.egg-info/SOURCES.txt
sqlite_spellfix.egg-info/dependency_links.txt
sqlite_spellfix.egg-info/top_level.txt