Metadata-Version: 2.1
Name: sqlite-spellfix
Version: 1.1
Summary: Loadable spellfix1 extension for sqlite
Home-page: http://github.com/karlb/sqlite-spellfix
License-File: LICENSE
